chaosaddons/__init__.py
chaosaddons/controls/__init__.py
chaosaddons/controls/bypass.py
chaosaddons/controls/repeat.py
chaosaddons/controls/safeguards.py
chaosaddons/controls/synchronization.py
chaosaddons/utils/__init__.py
chaosaddons/utils/idle.py
chaostoolkit_addons-0.11.0.dist-info/METADATA
chaostoolkit_addons-0.11.0.dist-info/WHEEL
chaostoolkit_addons-0.11.0.dist-info/licenses/LICENSE
chaostoolkit_addons-0.11.0.dist-info/RECORD
