Metadata-Version: 2.1
Name: chaostoolkit-addons
Version: 0.11.0
Summary: Addons for your Chaos Toolkit experiments
Author-Email: Chaos Toolkit <contact@chaostoolkit.org>
License: Apache-2.0
Classifier: Development Status :: 4 - Beta
Classifier: Intended Audience :: Developers
Classifier: License :: Freely Distributable
Classifier: License :: OSI Approved :: Apache Software License
Classifier: Operating System :: OS Independent
Classifier: Programming Language :: Python
Classifier: Programming Language :: Python :: 3
Classifier: Programming Language :: Python :: 3.8
Classifier: Programming Language :: Python :: 3.9
Classifier: Programming Language :: Python :: 3.10
Classifier: Programming Language :: Python :: 3.11
Classifier: Programming Language :: Python :: 3.12
Classifier: Programming Language :: Python :: Implementation
Classifier: Programming Language :: Python :: Implementation :: CPython
Project-URL: Documentation, https://chaostoolkit.org
Project-URL: Repository, https://github.com/chaostoolkit/chaostoolkit-addons
Project-URL: Changelog, https://github.com/chaostoolkit/chaostoolkit-addons/blob/master/CHANGELOG.md
Requires-Python: >=3.8
Requires-Dist: chaostoolkit-lib>=1.42.1
